departure/renderer/pygamer/__init__.py
departure/renderer/pygamer/cli.py
departure/renderer/pygamer/renderer.py
departure_server_pygame-1.0.0.dist-info/METADATA
departure_server_pygame-1.0.0.dist-info/WHEEL
departure_server_pygame-1.0.0.dist-info/top_level.txt
departure_server_pygame-1.0.0.dist-info/RECORD
