Metadata-Version: 2.1
Name: departure-server-pygame
Version: 1.0.0
Summary: Pygame Departure board back end
Home-page: https://github.com/spujadas/departure-board-servers-python
Author: Sébastien Pujadas
Author-email: sebastien@pujadas.net
License: UNKNOWN
Platform: UNKNOWN
Classifier: Programming Language :: Python :: 3
Classifier: License :: OSI Approved :: MIT License
Classifier: Operating System :: OS Independent
Requires-Python: >=3.6
Requires-Dist: departure
Requires-Dist: pygame
